pyloras/__init__.py
pyloras/_common.py
pyloras/_gamus.py
pyloras/_loras.py
pyloras/_prowras.py
pyloras/_version.py
pyloras-0.1.0b6.dist-info/LICENSE
pyloras-0.1.0b6.dist-info/METADATA
pyloras-0.1.0b6.dist-info/WHEEL
pyloras-0.1.0b6.dist-info/top_level.txt
pyloras-0.1.0b6.dist-info/RECORD
