Metadata-Version: 2.1
Name: pyloras
Version: 0.1.0b6
Summary: Experimental implementations of several (over/under)-sampling techniques not yet available in the imbalanced-learn library.
Author-email: Zolisa Bleki <zolisa.bleki@gmail.com>
License: BSD 3-Clause License
Project-URL: source, https://github.com/zoj613/pyloras
Project-URL: tracker, https://github.com/zoj613/pyloras/issues
Keywords: loras,imbalanced datasets,oversampling,machine learning,localized affine random shadowsampling
Classifier: Intended Audience :: Science/Research
Classifier: Topic :: Scientific/Engineering
Classifier: License :: OSI Approved :: BSD License
Classifier: Programming Language :: Python
Classifier: Programming Language :: Python :: 3 :: Only
Classifier: Operating System :: POSIX :: Linux
Classifier: Operating System :: Microsoft :: Windows :: Windows 10
Classifier: Operating System :: MacOS :: MacOS X
Requires-Python: >=3.8
License-File: LICENSE
Requires-Dist: numpy (>=1.17.3)
Requires-Dist: imbalanced-learn (<1.0.0)
